risk_kit/__init__.py
risk_kit/common/__init__.py
risk_kit/expert_scorecard/__init__.py
risk_kit/expert_scorecard/models/__init__.py
risk_kit/expert_scorecard/models/bucket.py
risk_kit/expert_scorecard/models/expert_scorecard.py
risk_kit/expert_scorecard/models/feature.py
risk_kit/expert_scorecard/ui/__init__.py
risk_kit/expert_scorecard/validation/__init__.py
risk_kit/expert_scorecard/validation/registry.py
risk_kit/expert_scorecard/validation/validators.py
risk_kit/expert_scorecard/visualisation/__init__.py
risk_kit/expert_scorecard/visualisation/visualiser.py
risk_kit-0.0.3.dist-info/LICENSE
risk_kit-0.0.3.dist-info/METADATA
risk_kit-0.0.3.dist-info/WHEEL
risk_kit-0.0.3.dist-info/entry_points.txt
risk_kit-0.0.3.dist-info/RECORD
