Metadata-Version: 2.3
Name: risk-kit
Version: 0.0.3
Summary: Open Source Python Package For Expert Risk Scorecards
License: MIT
Author: Sean Hickey
Author-email: sean.hickey@wayflyer.com
Requires-Python: >=3.10,<4
Classifier: License :: OSI Approved :: MIT License
Classifier: Programming Language :: Python :: 3
Classifier: Programming Language :: Python :: 3.10
Classifier: Programming Language :: Python :: 3.11
Classifier: Programming Language :: Python :: 3.12
Classifier: Programming Language :: Python :: 3.13
Requires-Dist: numpy (>=1.20.0)
Requires-Dist: pandas (>=1.3.0)
Requires-Dist: pydantic (>=2,<3)
Requires-Dist: scikit-learn (>=1.0.0)
Project-URL: Bug Tracker, https://github.com/sean-hickey-wf/risk-kit/issues
Project-URL: Documentation, https://risk-kit.readthedocs.io
Project-URL: Homepage, https://github.com/sean-hickey-wf/risk-kit
Project-URL: Repository, https://github.com/sean-hickey-wf/risk-kit
